pybizday_utils/__init__.py
pybizday_utils/_version.py
pybizday_utils/basic.py
pybizday_utils/date_range_utils.py
pybizday_utils/default_holiday_utils.py
pybizday_utils/holiday_utils.py
pybizday_utils/month.py
pybizday_utils/utils.py
pybizday_utils-0.0.0.dist-info/licenses/LICENSE
pybizday_utils-0.0.0.dist-info/METADATA
pybizday_utils-0.0.0.dist-info/WHEEL
pybizday_utils-0.0.0.dist-info/top_level.txt
pybizday_utils-0.0.0.dist-info/RECORD
