Metadata-Version: 2.4
Name: pybizday_utils
Version: 0.0.0
Summary: `pybizday_utils` is a Python library that provides utilities for calculating business days, including the ability to customize holidays and workdays.
Author-email: hmasdev <hmasuidev1com@gmail.com>
Maintainer-email: hmasdev <hmasuidev1com@gmail.com>
Project-URL: Homepage, https://github.com/hmasdev/pybizday_utils
Project-URL: Repository, https://github.com/hmasdev/pybizday_utils
Keywords: business day,utility,holiday,calendar
Classifier: Development Status :: 2 - Pre-Alpha
Classifier: Programming Language :: Python :: 3.10
Classifier: Programming Language :: Python :: 3.11
Classifier: Programming Language :: Python :: 3.12
Classifier: Programming Language :: Python :: 3.13
Requires-Python: >=3.10
License-File: LICENSE
Requires-Dist: python-dateutil>=2.9.0.post0
Requires-Dist: types-python-dateutil>=2.9.0.20241206
Provides-Extra: dev
Requires-Dist: autopep8>=2.3.2; extra == "dev"
Requires-Dist: build>=1.2.2.post1; extra == "dev"
Requires-Dist: mypy>=1.15.0; extra == "dev"
Requires-Dist: nox>=2025.2.9; extra == "dev"
Requires-Dist: pytest>=8.3.5; extra == "dev"
Requires-Dist: pytest-cov>=6.0.0; extra == "dev"
Requires-Dist: pytest-mock>=3.14.0; extra == "dev"
Requires-Dist: ruff>=0.11.2; extra == "dev"
Requires-Dist: twine>=6.1.0; extra == "dev"
Dynamic: license-file
